falconclaw/__init__.py
falconclaw/bite.py
falconclaw-0.0.4.dist-info/METADATA
falconclaw-0.0.4.dist-info/WHEEL
falconclaw-0.0.4.dist-info/licenses/LICENSE
falconclaw-0.0.4.dist-info/RECORD
