Metadata-Version: 2.3
Name: falconclaw
Version: 0.0.4
Summary: A package for Network Operations
Project-URL: Homepage, https://github.com/pypa/falconclaw
Project-URL: Issues, https://github.com/pypa/falconclaw/issues
Author-email: Juan Miguel Abreo Camacho <jmabreo@gmail.com>
License-File: LICENSE
Classifier: License :: OSI Approved :: MIT License
Classifier: Operating System :: OS Independent
Classifier: Programming Language :: Python :: 3
Classifier: Topic :: System :: Networking
Requires-Python: >=3.8
